run_with_logger/__init__.py
run_with_logger/_pipe_capture.py
run_with_logger/_pipe_to_logger.py
run_with_logger/_run_with_logger.py
run_with_logger/_types.py
run_with_logger/py.typed
run_with_logger/version.py
run_with_logger-1.0.0.dist-info/LICENSE
run_with_logger-1.0.0.dist-info/METADATA
run_with_logger-1.0.0.dist-info/WHEEL
run_with_logger-1.0.0.dist-info/top_level.txt
run_with_logger-1.0.0.dist-info/RECORD
