Metadata-Version: 2.1
Name: run_with_logger
Version: 1.0.0
Summary: Like `subprocess.run`, but with the ability to pipe `stdout` and/or `stderr` to a `Logger` or capture each stream independently while the process is running.
Author-email: Rudolf Byker <rudolfbyker@gmail.com>
Project-URL: repository, https://github.com/rudolfbyker/run_with_logger
Classifier: Programming Language :: Python :: 3
Classifier: License :: Other/Proprietary License
Classifier: Operating System :: OS Independent
Requires-Python: >=3.11
License-File: LICENSE
